README.rst
setup.py
VUnits.egg-info/PKG-INFO
VUnits.egg-info/SOURCES.txt
VUnits.egg-info/dependency_links.txt
VUnits.egg-info/not-zip-safe
VUnits.egg-info/requires.txt
VUnits.egg-info/top_level.txt
vunits/__init__.py
vunits/constants.py
vunits/convert.py
vunits/parse.py
vunits/quantity.py
vunits/db/__init__.py
vunits/db/unit_db.json
vunits/tests/__init__.py
vunits/tests/test_constants.py
vunits/tests/test_constants.xlsx
vunits/tests/test_convert.py
vunits/tests/test_convert.xlsx
vunits/tests/test_parse.py
vunits/tests/test_quantity.py