Metadata-Version: 2.1
Name: VUnits
Version: 0.0.3
Summary: Virtual Kinetic Laboratory Units (VUnits)
Home-page: https://github.com/VlachosGroup/vunits
Author: Vlachos Research Group
Author-email: vlachos@udel.edu
License: UNKNOWN
Platform: UNKNOWN
Classifier: Programming Language :: Python :: 3
Classifier: License :: OSI Approved :: MIT License
Classifier: Operating System :: OS Independent
Classifier: Intended Audience :: Science/Research
Classifier: Topic :: Scientific/Engineering :: Chemistry
